sep_pjw.cpython-39-darwin.so
_version.py
sep_pjw-1.3.8.dist-info/AUTHORS.md
sep_pjw-1.3.8.dist-info/RECORD
sep_pjw-1.3.8.dist-info/WHEEL
sep_pjw-1.3.8.dist-info/top_level.txt
sep_pjw-1.3.8.dist-info/METADATA
