Metadata-Version: 2.2
Name: sep-pjw
Version: 1.3.8
Summary: Astronomical source extraction and photometry library
Author: Emmanuel Bertin, Kyle Barbary, Kyle Boone, Thomas Robitaille, Matt Craig, Curtis McCully, Evert Rol, Joe Lyman, Michael Wuertenberger, Ingvar Stepanyan, Gabe Brammer, Peter Watson
Maintainer-email: Peter Watson <peter.watson+sep@inaf.it>
License: LGPLv3+
Project-URL: Homepage, https://github.com/PJ-Watson/sep-pjw
Project-URL: Bug Tracker, https://github.com/PJ-Watson/sep-pjw/issues
Project-URL: Documentation, http://sep-pjw.readthedocs.org
Classifier: Development Status :: 5 - Production/Stable
Classifier: Programming Language :: Python :: 3
Classifier: License :: OSI Approved :: GNU Lesser General Public License v3 or later (LGPLv3+)
Classifier: Topic :: Scientific/Engineering :: Astronomy
Classifier: Intended Audience :: Science/Research
Requires-Python: >=3.9
License-File: AUTHORS.md
Requires-Dist: numpy>=1.23.5
Requires-Dist: sep>=1.4.0
Provides-Extra: docs
Requires-Dist: sphinx-copybutton>=0.5; extra == "docs"
Requires-Dist: sphinx>=7.2; extra == "docs"
Requires-Dist: numpydoc>=1.6; extra == "docs"
Requires-Dist: matplotlib>=3.6; extra == "docs"
Requires-Dist: furo>=2024.1; extra == "docs"
Requires-Dist: nbsphinx>=0.9.3; extra == "docs"
Requires-Dist: pandoc>=2.3; extra == "docs"
Requires-Dist: fitsio>=1.2.1; extra == "docs"
Requires-Dist: jupyter; extra == "docs"
Requires-Dist: myst-parser>=2.0.0; extra == "docs"
